{
	"name": "SourceDataset_0eg",
	"properties": {
		"linkedServiceName": {
			"referenceName": "AzureDataLakeStorage1",
			"type": "LinkedServiceReference"
		},
		"annotations": [],
		"type": "DelimitedText",
		"typeProperties": {
			"location": {
				"type": "AzureBlobFSLocation",
				"folderPath": "inputdata",
				"fileSystem": "prasadcontainer"
			},
			"columnDelimiter": ";",
			"escapeChar": "\\",
			"firstRowAsHeader": true,
			"quoteChar": "\""
		},
		"schema": [
			{
				"name": "id",
				"type": "String"
			},
			{
				"name": "name",
				"type": "String"
			},
			{
				"name": "villege",
				"type": "String"
			},
			{
				"name": "dob",
				"type": "String"
			}
		]
	}
}